fins/__init__.py
fins/fins_common.py
fins/tcp.py
fins/udp.py
fins/usb.py
fins-1.0.5.dist-info/METADATA
fins-1.0.5.dist-info/WHEEL
fins-1.0.5.dist-info/license.txt
fins-1.0.5.dist-info/top_level.txt
fins-1.0.5.dist-info/RECORD
