Metadata-Version: 2.1
Name: fins
Version: 1.0.5
Summary: A library to communicate with Omron controllers using Factory Intelligent Network Service (FINS)
Home-page: https://github.com/aphyt/omron_fins
Author: Joseph Ryan
Author-email: jr@aphyt.com
License: UNKNOWN
Platform: UNKNOWN
Classifier: Programming Language :: Python :: 3
Classifier: License :: OSI Approved :: GNU General Public License v2 (GPLv2)
Classifier: Operating System :: OS Independent
Requires-Python: >=3.7
License-File: license.txt
